{
  "generator-jhipster": {
    "applicationType": "monolith",
    "authenticationType": "jwt",
    "baseName": "bugTrackerJHipster",
    "buildTool": "maven",
    "cacheProvider": "ehcache",
    "clientFramework": "angular",
    "clientTestFrameworks": ["cypress"],
    "clientTheme": "none",
    "creationTimestamp": 1707697010873,
    "cypressAudit": true,
    "cypressCoverage": true,
    "databaseType": "sql",
    "devDatabaseType": "h2Disk",
    "devServerPort": 4200,
    "enableGradleEnterprise": null,
    "enableHibernateCache": true,
    "enableSwaggerCodegen": false,
    "enableTranslation": true,
    "entities": [],
    "feignClient": false,
    "gradleEnterpriseHost": null,
    "jhipsterVersion": "8.1.0",
    "jwtSecretKey": "ZDkyYzkxOGNlNzRjZDMwNTI5NGUwOWQxODU2Y2M1NTNmOTMwZmRmZjQxODMxMTVhMGZiN2FmOThiYjU4MzRlNzc3YWQyMGNlN2ZmMWFkZjQyNzhkYWZiNjMzNmU4NWFmNzY3YWI5ZTNmYThmZGE1OTgxMDE4Mjg5ZTU3YTI4NDE=",
    "languages": ["en"],
    "messageBroker": false,
    "microfrontend": null,
    "microfrontends": [],
    "nativeLanguage": "en",
    "packageName": "com.mycompany.myapp",
    "prodDatabaseType": "postgresql",
    "reactive": false,
    "searchEngine": false,
    "serverPort": null,
    "serverSideOptions": [],
    "serviceDiscoveryType": false,
    "testFrameworks": ["gatling", "cypress"],
    "websocket": false,
    "withAdminUi": true
  }
}
